inc_counter/__init__.py
inc_counter/app.py
inc_counter/static/asset-manifest.json
inc_counter/static/favicon.ico
inc_counter/static/logo192.png
inc_counter/static/logo512.png
inc_counter/static/manifest.json
inc_counter/static/robots.txt
inc_counter/static/css/main.dfc1a0c4.css
inc_counter/static/css/main.dfc1a0c4.css.map
inc_counter/static/js/453.8ab44547.chunk.js
inc_counter/static/js/453.8ab44547.chunk.js.map
inc_counter/static/js/main.d8116eb0.js
inc_counter/static/js/main.d8116eb0.js.LICENSE.txt
inc_counter/static/js/main.d8116eb0.js.map
inc_counter/templates/index.html
inc_counter-0.9.dist-info/METADATA
inc_counter-0.9.dist-info/WHEEL
inc_counter-0.9.dist-info/entry_points.txt
inc_counter-0.9.dist-info/top_level.txt
inc_counter-0.9.dist-info/RECORD
